odoo10_addon_hr_employee_category_parent-10.0.1.0.0-py2.7-nspkg.pth
odoo/addons/hr_employee_category_parent/README.rst
odoo/addons/hr_employee_category_parent/__init__.py
odoo/addons/hr_employee_category_parent/__manifest__.py
odoo/addons/hr_employee_category_parent/demo/hr_employee_category.xml
odoo/addons/hr_employee_category_parent/models/__init__.py
odoo/addons/hr_employee_category_parent/models/hr_employee_category.py
odoo/addons/hr_employee_category_parent/static/description/icon.png
odoo/addons/hr_employee_category_parent/tests/__init__.py
odoo/addons/hr_employee_category_parent/tests/test_hr_employee_category_parent.py
odoo/addons/hr_employee_category_parent/views/hr_employee_category.xml
odoo10_addon_hr_employee_category_parent-10.0.1.0.0.dist-info/DESCRIPTION.rst
odoo10_addon_hr_employee_category_parent-10.0.1.0.0.dist-info/METADATA
odoo10_addon_hr_employee_category_parent-10.0.1.0.0.dist-info/RECORD
odoo10_addon_hr_employee_category_parent-10.0.1.0.0.dist-info/WHEEL
odoo10_addon_hr_employee_category_parent-10.0.1.0.0.dist-info/metadata.json
odoo10_addon_hr_employee_category_parent-10.0.1.0.0.dist-info/namespace_packages.txt
odoo10_addon_hr_employee_category_parent-10.0.1.0.0.dist-info/top_level.txt
